README.md
setup.py
l2logger/__init__.py
l2logger/__version__.py
l2logger/aggregate.py
l2logger/l2logger.py
l2logger/util.py
l2logger/validate.py
l2logger.egg-info/PKG-INFO
l2logger.egg-info/SOURCES.txt
l2logger.egg-info/dependency_links.txt
l2logger.egg-info/requires.txt
l2logger.egg-info/top_level.txt
test/test_simple_logging.py