Metadata-Version: 2.1
Name: l2logger
Version: 1.8.0
Summary: Lifelong learning logger
Home-page: https://github.com/darpa-l2m/l2logger
Author: Eric Nguyen
Author-email: Eric.Nguyen@jhuapl.edu
License: MIT
Download-URL: https://github.com/darpa-l2m/l2logger/archive/v1.8.0.tar.gz
Platform: UNKNOWN
Classifier: Development Status :: 3 - Alpha
Classifier: License :: OSI Approved :: MIT License
Classifier: Programming Language :: Python :: 3
Classifier: Programming Language :: Python :: 3.6
Classifier: Programming Language :: Python :: 3.7
Classifier: Programming Language :: Python :: 3.8
Classifier: Topic :: Scientific/Engineering :: Artificial Intelligence
